tomlserializer/__init__.py
tomlserializer/main.py
tomlserializer-0.2.0.dist-info/METADATA
tomlserializer-0.2.0.dist-info/WHEEL
tomlserializer-0.2.0.dist-info/RECORD
