Metadata-Version: 2.4
Name: tomlserializer
Version: 0.2.0
Summary: Add your description here
Author-email: raoul grouls <Raoul.Grouls@han.nl>
Requires-Python: >=3.11
Requires-Dist: loguru>=0.7.3
